bluestoned/__init__.py
bluestoned/main.py
bluestoned-0.1.1.dist-info/entry_points.txt
bluestoned-0.1.1.dist-info/LICENSE
bluestoned-0.1.1.dist-info/WHEEL
bluestoned-0.1.1.dist-info/METADATA
bluestoned-0.1.1.dist-info/RECORD
